my_module/__init__.py
my_module/module.py
mymo-1.0.dist-info/METADATA
mymo-1.0.dist-info/WHEEL
mymo-1.0.dist-info/top_level.txt
mymo-1.0.dist-info/RECORD
