Metadata-Version: 2.2
Name: mymo
Version: 1.0
Summary: sample module
Author: mohamed1234
Author-email: mohamedhathim628@gmail.com
Requires-Python: >=3.6
Dynamic: author
Dynamic: author-email
Dynamic: requires-python
Dynamic: summary
